[{"id":"88e3aa95.e70a38","type":"tab","label":"Flow 1","disabled":false,"info":""},{"id":"eae6e55f.993238","type":"rpi-gpio in","z":"88e3aa95.e70a38","name":"Button","pin":"7","intype":"up","debounce":"25","read":true,"x":100,"y":160,"wires":[["2ab388bc.a4a4d8","ae744365.890ac"]]},{"id":"ae744365.890ac","type":"rpi-gpio out","z":"88e3aa95.e70a38","name":"LED","pin":"11","set":"","level":"0","freq":"","out":"out","x":680,"y":160,"wires":[]},{"id":"2ab388bc.a4a4d8","type":"debug","z":"88e3aa95.e70a38","name":"msg.payload","active":true,"tosidebar":true,"console":false,"tostatus":false,"complete":"payload","targetType":"msg","x":280,"y":60,"wires":[]}]